multiHGtest/__init__.py
multiHGtest/multiHGtest.py
multihgtest-0.0.5.dist-info/licenses/LICENSE
multihgtest-0.0.5.dist-info/METADATA
multihgtest-0.0.5.dist-info/WHEEL
multihgtest-0.0.5.dist-info/top_level.txt
multihgtest-0.0.5.dist-info/RECORD
