Metadata-Version: 2.4
Name: multiHGtest
Version: 0.0.5
Summary: Testing for differences in survival using hypergeometric P-values
Home-page: https://github.com/alonkipnis/multiHGtest_package
Download-URL: https://github.com/alonkipnis/multiHGtest_package
Author: Alon Kipnis
Author-email: Alon Kipnis <alonkipnis@gmail.com>
License-Expression: MIT
Project-URL: Homepage, https://github.com/alonkipnis/higher-criticism-test
Project-URL: Repository, https://github.com/alonkipnis/higher-criticism-test
Classifier: Programming Language :: Python :: 3
Classifier: Operating System :: OS Independent
Requires-Python: >=3.6
License-File: LICENSE
Requires-Dist: numpy>=1.20
Requires-Dist: scipy>=1.7
Requires-Dist: pandas>=1.3
Requires-Dist: multiple-hypothesis-testing
Dynamic: download-url
Dynamic: license-file
